simple_coroutine/__init__.py
simple_coroutine/manager.py
simple_coroutine-0.1.5.dist-info/METADATA
simple_coroutine-0.1.5.dist-info/WHEEL
simple_coroutine-0.1.5.dist-info/RECORD
